enhanced_curation/__init__.py
enhanced_curation/apps.py
enhanced_curation/models.py
enhanced_curation/urls.py
enhanced_curation/views.py
enhanced_curation/cache_rebuilder/__init__.py
enhanced_curation/cache_rebuilder/apps.py
enhanced_curation/cache_rebuilder/background.py
enhanced_curation/migrations/0001_initial.py
enhanced_curation/migrations/0002_alter_documentcache_org_budget_and_more.py
enhanced_curation/migrations/0003_alter_collectioncache_last_run.py
enhanced_curation/migrations/0004_documentcache_priority_populations_and_more.py
enhanced_curation/migrations/0005_documentcache_top25percent.py
enhanced_curation/migrations/0006_documentcache_has_achievement_level_and_more.py
enhanced_curation/migrations/__init__.py
django_torque_enhanced_curation-0.2.0.dist-info/METADATA
django_torque_enhanced_curation-0.2.0.dist-info/WHEEL
django_torque_enhanced_curation-0.2.0.dist-info/top_level.txt
django_torque_enhanced_curation-0.2.0.dist-info/RECORD
